odoo/addons/partner_contact_in_several_companies/README.rst
odoo/addons/partner_contact_in_several_companies/__init__.py
odoo/addons/partner_contact_in_several_companies/__manifest__.py
odoo/addons/partner_contact_in_several_companies/demo/ir_actions.xml
odoo/addons/partner_contact_in_several_companies/demo/res_partner.xml
odoo/addons/partner_contact_in_several_companies/i18n/am.po
odoo/addons/partner_contact_in_several_companies/i18n/ar.po
odoo/addons/partner_contact_in_several_companies/i18n/bg.po
odoo/addons/partner_contact_in_several_companies/i18n/bs.po
odoo/addons/partner_contact_in_several_companies/i18n/ca.po
odoo/addons/partner_contact_in_several_companies/i18n/cs.po
odoo/addons/partner_contact_in_several_companies/i18n/da.po
odoo/addons/partner_contact_in_several_companies/i18n/de.po
odoo/addons/partner_contact_in_several_companies/i18n/el_GR.po
odoo/addons/partner_contact_in_several_companies/i18n/en_GB.po
odoo/addons/partner_contact_in_several_companies/i18n/es.po
odoo/addons/partner_contact_in_several_companies/i18n/es_CO.po
odoo/addons/partner_contact_in_several_companies/i18n/es_CR.po
odoo/addons/partner_contact_in_several_companies/i18n/es_EC.po
odoo/addons/partner_contact_in_several_companies/i18n/es_MX.po
odoo/addons/partner_contact_in_several_companies/i18n/es_VE.po
odoo/addons/partner_contact_in_several_companies/i18n/et.po
odoo/addons/partner_contact_in_several_companies/i18n/eu.po
odoo/addons/partner_contact_in_several_companies/i18n/fi.po
odoo/addons/partner_contact_in_several_companies/i18n/fr.po
odoo/addons/partner_contact_in_several_companies/i18n/fr_CA.po
odoo/addons/partner_contact_in_several_companies/i18n/fr_CH.po
odoo/addons/partner_contact_in_several_companies/i18n/gl.po
odoo/addons/partner_contact_in_several_companies/i18n/hr.po
odoo/addons/partner_contact_in_several_companies/i18n/hr_HR.po
odoo/addons/partner_contact_in_several_companies/i18n/hu.po
odoo/addons/partner_contact_in_several_companies/i18n/it.po
odoo13_addon_partner_contact_in_several_companies-13.0.1.1.0.dist-info/METADATA
odoo13_addon_partner_contact_in_several_companies-13.0.1.1.0.dist-info/WHEEL
odoo13_addon_partner_contact_in_several_companies-13.0.1.1.0.dist-info/top_level.txt
odoo13_addon_partner_contact_in_several_companies-13.0.1.1.0.dist-info/RECORD
