Metadata-Version: 2.1
Name: odoo13-addon-partner-contact-in-several-companies
Version: 13.0.1.1.0
Summary: Allow to have one contact in several partners
Home-page: https://github.com/OCA/partner-contact
Author: Nicolas JEUDY, Odoo Community Association (OCA),Odoo SA
Author-email: support@odoo-community.org
License: AGPL-3
Platform: UNKNOWN
Classifier: Programming Language :: Python
Classifier: Framework :: Odoo
Classifier: License :: OSI Approved :: GNU Affero General Public License v3
Requires-Python: >=3.5
Requires-Dist: odoo13-addon-partner-contact-personal-information-page
Requires-Dist: odoo (<13.1dev,>=13.0a)
